recorder_mock/Makefile
recorder_mock/__init__.py
recorder_mock-0.0.1.dist-info/METADATA
recorder_mock-0.0.1.dist-info/WHEEL
recorder_mock-0.0.1.dist-info/licenses/LICENSE
recorder_mock-0.0.1.dist-info/RECORD
