Metadata-Version: 2.1
Name: recorder-mock
Version: 0.0.1
Summary: recorder-mock allows to record interactions on patched Python objects and repeat the interactions when the patched object is no longer available.
Author-email: Albertas Gimbutas <albertasgim@gmail.com>
License-File: LICENSE
Classifier: Development Status :: 3 - Alpha
Classifier: License :: OSI Approved :: GNU Affero General Public License v3
Classifier: Natural Language :: English
Classifier: Operating System :: OS Independent
Classifier: Programming Language :: Python
Classifier: Programming Language :: Python :: 3.8
Classifier: Programming Language :: Python :: 3.9
Classifier: Programming Language :: Python :: 3.10
Classifier: Programming Language :: Python :: 3.11
Requires-Python: >=3.8
